ntnx_datapolicies_py_client/__init__.py
ntnx_datapolicies_py_client/api_client.py
ntnx_datapolicies_py_client/api_response.py
ntnx_datapolicies_py_client/configuration.py
ntnx_datapolicies_py_client/custom_retry.py
ntnx_datapolicies_py_client/rest.py
ntnx_datapolicies_py_client/api/__init__.py
ntnx_datapolicies_py_client/api/entity_sync_policies_api.py
ntnx_datapolicies_py_client/api/protection_policies_api.py
ntnx_datapolicies_py_client/api/recovery_plans_api.py
ntnx_datapolicies_py_client/api/storage_policies_api.py
ntnx_datapolicies_py_client/models/__init__.py
ntnx_datapolicies_py_client/models/OneOfcommon/__init__.py
ntnx_datapolicies_py_client/models/OneOfcommon/v1/__init__.py
ntnx_datapolicies_py_client/models/OneOfcommon/v1/config/KVPairvalue.py
ntnx_datapolicies_py_client/models/OneOfcommon/v1/config/__init__.py
ntnx_datapolicies_py_client/models/OneOfdatapolicies/__init__.py
ntnx_datapolicies_py_client/models/OneOfdatapolicies/v4/__init__.py
ntnx_datapolicies_py_client/models/OneOfdatapolicies/v4/config/CreateConsistencyRuleApiResponsedata.py
ntnx_datapolicies_py_client/models/OneOfdatapolicies/v4/config/CreateDataServicesIpMappingApiResponsedata.py
ntnx_datapolicies_py_client/models/OneOfdatapolicies/v4/config/CreateNetworkMappingApiResponsedata.py
ntnx_datapolicies_py_client/models/OneOfdatapolicies/v4/config/CreateProtectionPolicyApiResponsedata.py
ntnx_datapolicies_py_client/models/OneOfdatapolicies/v4/config/CreateRecoveryPlanApiResponsedata.py
ntnx_datapolicies_py_client/models/OneOfdatapolicies/v4/config/CreateRecoverySettingApiResponsedata.py
ntnx_datapolicies_py_client/models/OneOfdatapolicies/v4/config/CreateRecoveryStageApiResponsedata.py
ntnx_datapolicies_py_client/models/OneOfdatapolicies/v4/config/CreateStoragePolicyApiResponsedata.py
ntnx_datapolicies_py_client/models/OneOfdatapolicies/v4/config/DeleteConsistencyRuleApiResponsedata.py
ntnx_datapolicies_py_client-4.2.1.dist-info/LICENSE.txt
ntnx_datapolicies_py_client-4.2.1.dist-info/METADATA
ntnx_datapolicies_py_client-4.2.1.dist-info/WHEEL
ntnx_datapolicies_py_client-4.2.1.dist-info/top_level.txt
ntnx_datapolicies_py_client-4.2.1.dist-info/RECORD
